python_video_thumbnail/__init__.py
python_video_thumbnail/video_frames.py
python_video_thumbnail-0.1.0.dist-info/AUTHORS.rst
python_video_thumbnail-0.1.0.dist-info/LICENSE
python_video_thumbnail-0.1.0.dist-info/METADATA
python_video_thumbnail-0.1.0.dist-info/WHEEL
python_video_thumbnail-0.1.0.dist-info/top_level.txt
python_video_thumbnail-0.1.0.dist-info/RECORD
