Metadata-Version: 2.1
Name: python-video-thumbnail
Version: 0.1.0
Summary: Python package for capturing frames from video.
Home-page: https://github.com/mikolajkosmal/python_video_thumbnail
Author: Mikolaj Kosmal
Author-email: mikolaj.kosmal@gmail.com
License: MIT license
Keywords: python_video_thumbnail
Platform: UNKNOWN
Classifier: Development Status :: 2 - Pre-Alpha
Classifier: Intended Audience :: Developers
Classifier: License :: OSI Approved :: MIT License
Classifier: Natural Language :: English
Classifier: Programming Language :: Python :: 2.7
Classifier: Programming Language :: Python :: 3.6
Classifier: Programming Language :: Python :: 3.7
Requires-Python: <3.9
Requires-Dist: opencv-python (==4.2.0.32)
